MANIFEST.in
README
setup.py
bqclient.egg-info/PKG-INFO
bqclient.egg-info/SOURCES.txt
bqclient.egg-info/dependency_links.txt
bqclient.egg-info/entry_points.txt
bqclient.egg-info/requires.txt
bqclient.egg-info/top_level.txt
bumblebee/__init__.py
bumblebee/__main__.py
bumblebee/_version.py
bumblebee/apitest.py
bumblebee/app.py
bumblebee/autoupgrade.py
bumblebee/botqueueapi.py
bumblebee/camera_control.py
bumblebee/config-dist.json
bumblebee/config.json
bumblebee/ginsu.py
bumblebee/hive.py
bumblebee/imagesnap
bumblebee/stacktracer.py
bumblebee/workerbee.py
bumblebee/drivers/__init__.py
bumblebee/drivers/bumbledriver.py
bumblebee/drivers/dummydriver.py
bumblebee/drivers/printcoredriver.py
bumblebee/drivers/s3gdriver.py