Metadata-Version: 1.0
Name: bqclient
Version: 0.5.4
Summary: BotQueue's client bumblebee
Home-page: http://github.com/Hoektronics/bumblebee/
Author: Justin Nesselrotte
Author-email: jnesselr@harding.edu
License: UNKNOWN
Platform: UNKNOWN
